visiontagger/__init__.py
visiontagger/__main__.py
visiontagger/icon.png
visiontagger/main.py
VisionTagger-0.2.0.dist-info/LICENCE
VisionTagger-0.2.0.dist-info/METADATA
VisionTagger-0.2.0.dist-info/WHEEL
VisionTagger-0.2.0.dist-info/entry_points.txt
VisionTagger-0.2.0.dist-info/top_level.txt
VisionTagger-0.2.0.dist-info/RECORD
