Metadata-Version: 2.1
Name: VisionTagger
Version: 0.2.0
License-File: LICENCE
Requires-Dist: pillow
Requires-Dist: opencv-python
Requires-Dist: tk
